grokfast_pytorch/__init__.py
grokfast_pytorch/grokfast.py
grokfast_pytorch-0.0.11.dist-info/METADATA
grokfast_pytorch-0.0.11.dist-info/WHEEL
grokfast_pytorch-0.0.11.dist-info/licenses/LICENSE
grokfast_pytorch-0.0.11.dist-info/RECORD
