Metadata-Version: 2.4
Name: grokfast-pytorch
Version: 0.0.11
Summary: Grokfast
Project-URL: Homepage, https://pypi.org/project/grokfast_pytorch/
Project-URL: Repository, https://github.com/lucidrains/grokfast-pytorch
Author-email: Phil Wang <lucidrains@gmail.com>
License: MIT License
License-File: LICENSE
Keywords: artificial intelligence,deep learning,grokking
Classifier: Development Status :: 4 - Beta
Classifier: Intended Audience :: Developers
Classifier: License :: OSI Approved :: MIT License
Classifier: Programming Language :: Python :: 3.9
Classifier: Topic :: Scientific/Engineering :: Artificial Intelligence
Requires-Python: >=3.9
Requires-Dist: torch>=2.0
Provides-Extra: examples
Provides-Extra: test
Requires-Dist: pytest; extra == 'test'
